megpy/__init__.py
megpy/__main__.py
megpy/cli.py
megpy/equilibrium.py
megpy/fluxsurface.py
megpy/io.py
megpy/localequilibrium.py
megpy/tracer.py
megpy/utils.py
megpy-2.0.5.dist-info/licenses/LICENSE
megpy-2.0.5.dist-info/METADATA
megpy-2.0.5.dist-info/WHEEL
megpy-2.0.5.dist-info/entry_points.txt
megpy-2.0.5.dist-info/top_level.txt
megpy-2.0.5.dist-info/RECORD
