Metadata-Version: 2.4
Name: megpy
Version: 2.0.5
Summary: megpy
Author-email: Garud Snoep <gsnoep42@gmail.com>, Aaron Ho <aaronkho@mit.edu>
License:                    GNU LESSER GENERAL PUBLIC LICENSE
Project-URL: Homepage, https://github.com/gsnoep/megpy
Project-URL: Bug Reports, https://github.com/gsnoep/megpy/issues
Project-URL: Source, https://github.com/gsnoep/megpy
Keywords: MHD,magnetic,equilibrium,toolkit,fusion,simulation
Classifier: Programming Language :: Python :: 3
Classifier: Operating System :: OS Independent
Requires-Python: >=3.8
License-File: LICENSE
Requires-Dist: numpy>=1.26.4
Requires-Dist: scipy
Requires-Dist: matplotlib
Requires-Dist: xarray
Requires-Dist: h5py
Provides-Extra: test
Requires-Dist: pytest; extra == "test"
Dynamic: license-file
